pydl4j/__init__.py
pydl4j/cli.py
pydl4j/docker.py
pydl4j/downloader.py
pydl4j/jarmgr.py
pydl4j/mvn.py
pydl4j/pom.py
pydl4j/progressbar.py
pydl4j/pydl4j.py
pydl4j-0.1.5.dist-info/DESCRIPTION.rst
pydl4j-0.1.5.dist-info/METADATA
pydl4j-0.1.5.dist-info/RECORD
pydl4j-0.1.5.dist-info/WHEEL
pydl4j-0.1.5.dist-info/entry_points.txt
pydl4j-0.1.5.dist-info/metadata.json
pydl4j-0.1.5.dist-info/top_level.txt
