Metadata-Version: 2.1
Name: pydl4j
Version: 0.1.5
Summary: Java dependency management for Python projects using DL4J
Home-page: https://github.com/deeplearning4j/pydl4j
License: Apache
Platform: UNKNOWN
Classifier: Development Status :: 3 - Alpha
Classifier: Intended Audience :: Developers
Classifier: Environment :: Console
Classifier: License :: OSI Approved :: Apache Software License
Classifier: Operating System :: OS Independent
Classifier: Programming Language :: Python
Classifier: Programming Language :: Python :: 2
Classifier: Programming Language :: Python :: 3
Provides-Extra: tests
